odoo/addons/sale_attached_product/README.rst
odoo/addons/sale_attached_product/__init__.py
odoo/addons/sale_attached_product/__manifest__.py
odoo/addons/sale_attached_product/i18n/es.po
odoo/addons/sale_attached_product/i18n/it.po
odoo/addons/sale_attached_product/i18n/sale_attached_product.pot
odoo/addons/sale_attached_product/models/__init__.py
odoo/addons/sale_attached_product/models/product_template.py
odoo/addons/sale_attached_product/models/sale_attached_product_mixin.py
odoo/addons/sale_attached_product/models/sale_order.py
odoo/addons/sale_attached_product/readme/CONFIGURE.md
odoo/addons/sale_attached_product/readme/CONTRIBUTORS.md
odoo/addons/sale_attached_product/readme/DESCRIPTION.md
odoo/addons/sale_attached_product/readme/USAGE.md
odoo/addons/sale_attached_product/static/description/icon.png
odoo/addons/sale_attached_product/static/description/index.html
odoo/addons/sale_attached_product/tests/__init__.py
odoo/addons/sale_attached_product/tests/test_sale_attached_product.py
odoo/addons/sale_attached_product/views/product_template_views.xml
odoo_addon_sale_attached_product-17.0.1.0.0.2.dist-info/METADATA
odoo_addon_sale_attached_product-17.0.1.0.0.2.dist-info/WHEEL
odoo_addon_sale_attached_product-17.0.1.0.0.2.dist-info/top_level.txt
odoo_addon_sale_attached_product-17.0.1.0.0.2.dist-info/RECORD
